glog.py
glog2-0.0.4.dist-info/LICENSE
glog2-0.0.4.dist-info/METADATA
glog2-0.0.4.dist-info/WHEEL
glog2-0.0.4.dist-info/top_level.txt
glog2-0.0.4.dist-info/RECORD
