Metadata-Version: 2.1
Name: glog2
Version: 0.0.4
Summary: Simple Google-style logging wrapper for Python. Forked from benley/python-glog
Home-page: https://github.com/moomou/python-glog
Author: Paul M
Author-email: ppymou@gmail.com
License: BSD
Platform: any
Classifier: Programming Language :: Python
Classifier: Development Status :: 4 - Beta
Classifier: Intended Audience :: Developers
Classifier: License :: OSI Approved :: BSD License
Classifier: Topic :: System :: Logging
Classifier: Topic :: Software Development :: Libraries :: Python Modules
Requires-Dist: python-gflags (>=3.1)
Requires-Dist: six
